{"Milk": {"SKUID": 101, "ITEM": "Milk", "ISLE": "A1", "QUANTITY": 42, "PRICE": 2.49, "UNIT": "Gallon", "TOTAL SALES": 44.82}, "Eggs": {"SKUID": 102, "ITEM": "Eggs", "ISLE": "A2", "QUANTITY": 33, "PRICE": 1.32, "UNIT": "Tray", "TOTAL SALES": 9.24}, "Bread": {"SKUID": 103, "ITEM": "Bread", "ISLE": "A3", "QUANTITY": 50, "PRICE": 1.32, "UNIT": "Loaf", "TOTAL SALES": 6.6}, "Apples": {"SKUID": 104, "ITEM": "Apples", "ISLE": "A4", "QUANTITY": 50, "PRICE": 1.49, "UNIT": "Pound", "TOTAL SALES": 0}, "Tomatoes": {"SKUID": 105, "ITEM": "Tomatoes", "ISLE": "A5", "QUANTITY": 87, "PRICE": 1.1, "UNIT": "Pound", "TOTAL SALES": 0}}